multi_elo/__init__.py
multi_elo/multi_elo.py
multi_elo/test_multi_elo.py
multi_elo-2.0.0.dist-info/LICENSE
multi_elo-2.0.0.dist-info/METADATA
multi_elo-2.0.0.dist-info/WHEEL
multi_elo-2.0.0.dist-info/top_level.txt
multi_elo-2.0.0.dist-info/RECORD
