Metadata-Version: 2.1
Name: multi-elo
Version: 2.0.0
Summary: ELO score calculator for more than two players
Home-page: https://github.com/qwhex/multi_elo
Author: Mice Pápai
Author-email: qwhexz@gmail.com
License: Apache-2.0
Keywords: elo elo-score chess ranking multiplayer scoring score rating
Platform: UNKNOWN
Classifier: Development Status :: 3 - Alpha
Classifier: Intended Audience :: Developers
Classifier: Topic :: Games/Entertainment
Classifier: Topic :: Games/Entertainment :: Board Games
Classifier: License :: OSI Approved :: Apache Software License
Classifier: Operating System :: OS Independent
Classifier: Programming Language :: Python :: 3 :: Only
Classifier: Programming Language :: Python :: 3.5
Classifier: Programming Language :: Python :: 3.6
Classifier: Programming Language :: Python :: 3.7
